LICENSE
README.md
setup.py
provreq.egg-info/PKG-INFO
provreq.egg-info/SOURCES.txt
provreq.egg-info/dependency_links.txt
provreq.egg-info/entry_points.txt
provreq.egg-info/namespace_packages.txt
provreq.egg-info/requires.txt
provreq.egg-info/top_level.txt
provreq.egg-info/zip-safe
provreq/tools/__init__.py
provreq/tools/config.py
provreq/tools/format_json.py
provreq/tools/generate.py
provreq/tools/promise_search.py
provreq/tools/promise_usage.py
provreq/tools/show_agent.py
provreq/tools/show_bundle.py
provreq/tools/show_promise.py
provreq/tools/libs/__init__.py
provreq/tools/libs/data.py
provreq/tools/libs/libgenerate.py
provreq/tools/libs/types.py
tests/test_checks.py
tests/test_files.py
tests/test_inheritance.py
tests/test_levenshtein.py
tests/test_simulate.py
tests/test_techniques.py
tests/test_types.py