Metadata-Version: 2.4
Name: provreq
Version: 0.1.6
Summary: Provreq
Home-page: https://github.com/mnemonic-no/provreq
Author: mnemonic AS
Author-email: opensource@mnemonic.no
License: MIT
Keywords: provreq,attack,mnemonic
Classifier: Development Status :: 4 - Beta
Classifier: Topic :: Utilities
Classifier: License :: OSI Approved :: ISC License (ISCL)
Requires-Python: >=3.6, <4
License-File: LICENSE
Requires-Dist: tabulate
Requires-Dist: pytest
Requires-Dist: pydantic
Requires-Dist: pyattck
Requires-Dist: caep
Dynamic: author
Dynamic: author-email
Dynamic: classifier
Dynamic: description
Dynamic: description-content-type
Dynamic: home-page
Dynamic: keywords
Dynamic: license
Dynamic: license-file
Dynamic: requires-dist
Dynamic: requires-python
Dynamic: summary
